MPGLGrid.cp311-win_amd64.pyd
MPGLGrid/MPGLGrid.cp311-win_amd64.pyd
MPGLGrid/__init__.py
MPGLGrid/include/MPGLGrid.h
MPGLGrid-0.0.0.dist-info/LICENSE
MPGLGrid-0.0.0.dist-info/METADATA
MPGLGrid-0.0.0.dist-info/WHEEL
MPGLGrid-0.0.0.dist-info/top_level.txt
MPGLGrid-0.0.0.dist-info/RECORD
