Metadata-Version: 2.1
Name: MPGLGrid
Version: 0.0.0
Summary: Visualization of MPGrid results using OpenGL
Author-email: Kenjiro Sugio <ksugio@hiroshima-u.ac.jp>
License: MIT License
Project-URL: Homepage, https://github.com/ksugio/MPGLGrid
Classifier: Development Status :: 4 - Beta
Classifier: Programming Language :: Python
Classifier: Programming Language :: Python :: 3
Requires-Python: >=3.8
License-File: LICENSE
Requires-Dist: numpy
Requires-Dist: MPGrid
Provides-Extra: dev
Requires-Dist: build ; extra == 'dev'
Requires-Dist: twine ; extra == 'dev'
